[{"cyclomatic":1,"cyclomaticDensity":50,"halstead":{"bugs":0.006,"difficulty":2,"effort":36.189,"length":7,"time":2.011,"vocabulary":6,"volume":18.095,"operands":{"distinct":3,"total":4,"identifiers":["Promise","resolve","reject"]},"operators":{"distinct":3,"total":3,"identifiers":["return","new","function=>"]}},"paramCount":5,"sloc":{"logical":2,"physical":21},"errors":[],"lineEnd":30,"lineStart":10,"name":"pTimeout","paramNames":["promise","ms","clearTimeout","setTimeout","onTimeout"],"maxNestedMethodDepth":0,"nestedMethods":[]},{"cyclomatic":1,"cyclomaticDensity":16.667,"halstead":{"bugs":0.018,"difficulty":2.5,"effort":134.436,"length":15,"time":7.469,"vocabulary":12,"volume":53.774,"operands":{"distinct":7,"total":7,"identifiers":["timer","setTimeout","ms","promise","then","val","err"]},"operators":{"distinct":5,"total":8,"identifiers":["const","=","()","function=>","."]}},"paramCount":2,"sloc":{"logical":6,"physical":13},"errors":[],"lineEnd":29,"lineStart":17,"name":"<anon method-1>","paramNames":["resolve","reject"],"maxNestedMethodDepth":0,"nestedMethods":[]},{"cyclomatic":1,"cyclomaticDensity":33.333,"halstead":{"bugs":0.002,"difficulty":0.5,"effort":3.17,"length":4,"time":0.176,"vocabulary":3,"volume":6.34,"operands":{"distinct":2,"total":2,"identifiers":["resolve","onTimeout"]},"operators":{"distinct":1,"total":2,"identifiers":["()"]}},"paramCount":0,"sloc":{"logical":3,"physical":1},"errors":[],"lineEnd":18,"lineStart":18,"name":"<anon method-2>","paramNames":[],"maxNestedMethodDepth":0,"nestedMethods":[]},{"cyclomatic":1,"cyclomaticDensity":50,"halstead":{"bugs":0.005,"difficulty":0.5,"effort":6.966,"length":6,"time":0.387,"vocabulary":5,"volume":13.932,"operands":{"distinct":4,"total":4,"identifiers":["clearTimeout","timer","resolve","val"]},"operators":{"distinct":1,"total":2,"identifiers":["()"]}},"paramCount":1,"sloc":{"logical":2,"physical":4},"errors":[],"lineEnd":23,"lineStart":20,"name":"<anon method-3>","paramNames":["val"],"maxNestedMethodDepth":0,"nestedMethods":[]},{"cyclomatic":1,"cyclomaticDensity":50,"halstead":{"bugs":0.005,"difficulty":0.5,"effort":6.966,"length":6,"time":0.387,"vocabulary":5,"volume":13.932,"operands":{"distinct":4,"total":4,"identifiers":["clearTimeout","timer","reject","err"]},"operators":{"distinct":1,"total":2,"identifiers":["()"]}},"paramCount":1,"sloc":{"logical":2,"physical":4},"errors":[],"lineEnd":27,"lineStart":24,"name":"<anon method-4>","paramNames":["err"],"maxNestedMethodDepth":0,"nestedMethods":[]}]