[{"cyclomatic":3,"cyclomaticDensity":300,"halstead":{"bugs":0.016,"difficulty":3.5,"effort":162.774,"length":14,"time":9.043,"vocabulary":10,"volume":46.507,"operands":{"distinct":5,"total":7,"identifiers":["val","constructor","\"function\"","name","\"Object\""]},"operators":{"distinct":5,"total":7,"identifiers":["||","&&","===","typeof (prefix)","."]}},"paramCount":1,"sloc":{"logical":1,"physical":2},"errors":[],"lineEnd":62,"lineStart":61,"name":"<anon method-1>","paramNames":["val"],"maxNestedMethodDepth":0,"nestedMethods":[]},{"cyclomatic":2,"cyclomaticDensity":200,"halstead":{"bugs":0.007,"difficulty":2.667,"effort":59.89,"length":8,"time":3.327,"vocabulary":7,"volume":22.459,"operands":{"distinct":3,"total":4,"identifiers":["window","\"undefined\"","val"]},"operators":{"distinct":4,"total":4,"identifiers":["&&","!==","typeof (prefix)","==="]}},"paramCount":1,"sloc":{"logical":1,"physical":2},"errors":[],"lineEnd":67,"lineStart":66,"name":"<anon method-2>","paramNames":["val"],"maxNestedMethodDepth":0,"nestedMethods":[]},{"cyclomatic":12,"cyclomaticDensity":1200,"halstead":{"bugs":0.064,"difficulty":2.769,"effort":531.692,"length":48,"time":29.538,"vocabulary":16,"volume":192,"operands":{"distinct":13,"total":24,"identifiers":["toStringed","\"[object Array]\"","\"[object ArrayBuffer]\"","\"[object DataView]\"","\"[object Float32Array]\"","\"[object Float64Array]\"","\"[object Int8Array]\"","\"[object Int16Array]\"","\"[object Int32Array]\"","\"[object Uint8Array]\"","\"[object Uint8ClampedArray]\"","\"[object Uint16Array]\"","\"[object Uint32Array]\""]},"operators":{"distinct":3,"total":24,"identifiers":["return","||","==="]}},"paramCount":1,"sloc":{"logical":1,"physical":16},"errors":[],"lineEnd":95,"lineStart":80,"name":"isToStringedArrayType","paramNames":["toStringed"],"maxNestedMethodDepth":0,"nestedMethods":[]},{"cyclomatic":2,"cyclomaticDensity":66.667,"halstead":{"bugs":0.015,"difficulty":2.917,"effort":131.17,"length":13,"time":7.287,"vocabulary":11,"volume":44.973,"operands":{"distinct":6,"total":7,"identifiers":["Object","is","val","0","\"-0\"","String"]},"operators":{"distinct":5,"total":6,"identifiers":["return",":?","()",".","- (prefix)"]}},"paramCount":1,"sloc":{"logical":3,"physical":3},"errors":[],"lineEnd":99,"lineStart":97,"name":"printNumber","paramNames":["val"],"maxNestedMethodDepth":0,"nestedMethods":[]},{"cyclomatic":1,"cyclomaticDensity":50,"halstead":{"bugs":0.007,"difficulty":2,"effort":39.303,"length":7,"time":2.183,"vocabulary":7,"volume":19.651,"operands":{"distinct":3,"total":3,"identifiers":["String","val","n"]},"operators":{"distinct":4,"total":4,"identifiers":["return","()","``","${}"]}},"paramCount":1,"sloc":{"logical":2,"physical":3},"errors":[],"lineEnd":103,"lineStart":101,"name":"printBigInt","paramNames":["val"],"maxNestedMethodDepth":0,"nestedMethods":[]},{"cyclomatic":3,"cyclomaticDensity":100,"halstead":{"bugs":0.019,"difficulty":3.5,"effort":199.886,"length":15,"time":11.105,"vocabulary":14,"volume":57.11,"operands":{"distinct":7,"total":7,"identifiers":["printFunctionName","\"[Function]\"","val","name","\"anonymous\"","[Function ","]"]},"operators":{"distinct":7,"total":8,"identifiers":["if","! (prefix)","return","``","${}","||","."]}},"paramCount":2,"sloc":{"logical":3,"physical":6},"errors":[],"lineEnd":110,"lineStart":105,"name":"printFunction","paramNames":["val","printFunctionName"],"maxNestedMethodDepth":0,"nestedMethods":[]},{"cyclomatic":1,"cyclomaticDensity":33.333,"halstead":{"bugs":0.009,"difficulty":1.5,"effort":40.5,"length":9,"time":2.25,"vocabulary":8,"volume":27,"operands":{"distinct":5,"total":5,"identifiers":["String","val","replace","SYMBOL_REGEXP","\"Symbol($1)\""]},"operators":{"distinct":3,"total":4,"identifiers":["return","()","."]}},"paramCount":1,"sloc":{"logical":3,"physical":3},"errors":[],"lineEnd":114,"lineStart":112,"name":"printSymbol","paramNames":["val"],"maxNestedMethodDepth":0,"nestedMethods":[]},{"cyclomatic":1,"cyclomaticDensity":50,"halstead":{"bugs":0.011,"difficulty":2.5,"effort":83.048,"length":10,"time":4.614,"vocabulary":10,"volume":33.219,"operands":{"distinct":5,"total":5,"identifiers":["errorToString","call","val","[","]"]},"operators":{"distinct":5,"total":5,"identifiers":["return","``","${}","()","."]}},"paramCount":1,"sloc":{"logical":2,"physical":3},"errors":[],"lineEnd":118,"lineStart":116,"name":"printError","paramNames":["val"],"maxNestedMethodDepth":0,"nestedMethods":[]},{"cyclomatic":22,"cyclomaticDensity":40.741,"halstead":{"bugs":0.357,"difficulty":14.636,"effort":15690.336,"length":183,"time":871.685,"vocabulary":58,"volume":1072.011,"operands":{"distinct":44,"total":92,"identifiers":["val","true","false","undefined","\"undefined\"","null","\"null\"","typeOf","\"number\"","printNumber","\"bigint\"","printBigInt","\"string\"","escapeString","replace","/\"|\\\\/g","\"\\$&\"","\"","\"function\"","printFunction","printFunctionName","\"symbol\"","printSymbol","toStringed","toString","call","\"[object WeakMap]\"","\"WeakMap {}\"","\"[object WeakSet]\"","\"WeakSet {}\"","\"[object Function]\"","\"[object GeneratorFunction]\"","\"[object Symbol]\"","\"[object Date]\"","isNaN","\"Date { NaN }\"","toISOString","\"[object Error]\"","printError","\"[object RegExp]\"","escapeRegex","regExpToString","/[\\\\^$*+?.()|[\\]{}]/g","Error"]},"operators":{"distinct":14,"total":91,"identifiers":["if","||","===","return","``","${}","const","=","typeof (prefix)","()",".",":?","+ (prefix)","instanceof"]}},"paramCount":4,"sloc":{"logical":54,"physical":74},"errors":[],"lineEnd":197,"lineStart":124,"name":"printBasicValue","paramNames":["val","printFunctionName","escapeRegex","escapeString"],"maxNestedMethodDepth":0,"nestedMethods":[]},{"cyclomatic":24,"cyclomaticDensity":68.571,"halstead":{"bugs":0.515,"difficulty":24.404,"effort":37693.676,"length":252,"time":2094.093,"vocabulary":70,"volume":1544.579,"operands":{"distinct":52,"total":141,"identifiers":["refs","indexOf","val","1","\"[Circular]\"","slice","push","hitMaxDepth","depth","config","maxDepth","min","callToJSON","toJSON","\"function\"","hasCalledToJSON","printer","indentation","true","toStringed","toString","call","\"[object Arguments]\"","\"[Arguments]\"","\"\"","\"Arguments \"","printListItems","[","]","isToStringedArrayType","constructor","name","printBasicPrototype","\"Array\""," ","\"[object Map]\"","\"[Map]\"","printIteratorEntries","entries","\" => \"","Map {","}","\"[object Set]\"","\"[Set]\"","printIteratorValues","values","Set {","isWindow","getConstructorName","\"Object\"","printObjectProperties","{"]},"operators":{"distinct":18,"total":111,"identifiers":["if","!==","()",".","- (prefix)","return","=","const",">","++ (prefix)","&&","! (prefix)","===","typeof (prefix)",":?","``","${}","||"]}},"paramCount":6,"sloc":{"logical":35,"physical":96},"errors":[],"lineEnd":298,"lineStart":203,"name":"printComplexValue","paramNames":["val","config","indentation","depth","refs","hasCalledToJSON"],"maxNestedMethodDepth":0,"nestedMethods":[]},{"cyclomatic":1,"cyclomaticDensity":100,"halstead":{"bugs":0.008,"difficulty":2.25,"effort":56.849,"length":9,"time":3.158,"vocabulary":7,"volume":25.266,"operands":{"distinct":4,"total":6,"identifiers":["plugin","NewPlugin","serialize","null"]},"operators":{"distinct":3,"total":3,"identifiers":["return","!=","."]}},"paramCount":1,"sloc":{"logical":1,"physical":3},"errors":[],"lineEnd":302,"lineStart":300,"name":"isNewPlugin","paramNames":["plugin"],"maxNestedMethodDepth":0,"nestedMethods":[]},{"cyclomatic":3,"cyclomaticDensity":18.75,"halstead":{"bugs":0.135,"difficulty":13.667,"effort":5554.094,"length":74,"time":308.561,"vocabulary":45,"volume":406.397,"operands":{"distinct":27,"total":41,"identifiers":["printed","isNewPlugin","plugin","serialize","val","config","indentation","depth","refs","printer","print","valChild","str","edgeSpacing","spacingOuter","min","spacing","spacingInner","colors","error","PrettyFormatPluginError","message","stack","\"string\"","Error","pretty-format: Plugin must return type \"string\" but instead returned \"","\"."]},"operators":{"distinct":18,"total":33,"identifiers":["let","try","=",":?","()",".","function=>","{}",":","catch","throw","new","if","!==","typeof (prefix)","``","${}","return"]}},"paramCount":6,"sloc":{"logical":16,"physical":40},"errors":[],"lineEnd":343,"lineStart":304,"name":"printPlugin","paramNames":["plugin","val","config","indentation","depth","refs"],"maxNestedMethodDepth":0,"nestedMethods":[]},{"cyclomatic":1,"cyclomaticDensity":50,"halstead":{"bugs":0.007,"difficulty":0.5,"effort":9.826,"length":7,"time":0.546,"vocabulary":7,"volume":19.651,"operands":{"distinct":6,"total":6,"identifiers":["printer","valChild","config","indentation","depth","refs"]},"operators":{"distinct":1,"total":1,"identifiers":["()"]}},"paramCount":1,"sloc":{"logical":2,"physical":1},"errors":[],"lineEnd":319,"lineStart":319,"name":"<anon method-3>","paramNames":["valChild"],"maxNestedMethodDepth":0,"nestedMethods":[]},{"cyclomatic":1,"cyclomaticDensity":33.333,"halstead":{"bugs":0.027,"difficulty":5,"effort":400,"length":20,"time":22.222,"vocabulary":16,"volume":80,"operands":{"distinct":8,"total":10,"identifiers":["indentationNext","indentation","config","indent","str","replace","NEWLINE_REGEXP","\n"]},"operators":{"distinct":8,"total":10,"identifiers":["const","=","+",".","return","()","``","${}"]}},"paramCount":1,"sloc":{"logical":3,"physical":7},"errors":[],"lineEnd":326,"lineStart":320,"name":"<anon method-4>","paramNames":["str"],"maxNestedMethodDepth":0,"nestedMethods":[]},{"cyclomatic":3,"cyclomaticDensity":37.5,"halstead":{"bugs":0.059,"difficulty":12.091,"effort":2133.641,"length":38,"time":118.536,"vocabulary":25,"volume":176.467,"operands":{"distinct":11,"total":19,"identifiers":["p","0","plugins","length","test","val","error","PrettyFormatPluginError","message","stack","null"]},"operators":{"distinct":14,"total":19,"identifiers":["for","let","=","<",".","++ (postfix)","try","if","()","[]","return","catch","throw","new"]}},"paramCount":2,"sloc":{"logical":8,"physical":13},"errors":[],"lineEnd":357,"lineStart":345,"name":"findPlugin","paramNames":["plugins","val"],"maxNestedMethodDepth":0,"nestedMethods":[]},{"cyclomatic":3,"cyclomaticDensity":27.273,"halstead":{"bugs":0.079,"difficulty":6.794,"effort":1619.84,"length":52,"time":89.991,"vocabulary":24,"volume":238.418,"operands":{"distinct":17,"total":33,"identifiers":["plugin","findPlugin","config","plugins","val","null","printPlugin","indentation","depth","refs","basicResult","printBasicValue","printFunctionName","escapeRegex","escapeString","printComplexValue","hasCalledToJSON"]},"operators":{"distinct":7,"total":19,"identifiers":["const","=","()",".","if","!==","return"]}},"paramCount":6,"sloc":{"logical":11,"physical":32},"errors":[],"lineEnd":390,"lineStart":359,"name":"printer","paramNames":["val","config","indentation","depth","refs","hasCalledToJSON"],"maxNestedMethodDepth":0,"nestedMethods":[]},{"cyclomatic":7,"cyclomaticDensity":70,"halstead":{"bugs":0.104,"difficulty":10.941,"effort":3401.73,"length":64,"time":188.985,"vocabulary":29,"volume":310.911,"operands":{"distinct":17,"total":31,"identifiers":["Object","keys","options","forEach","key","min","indent","undefined","0","Error","\"pretty-format: Options \"min\" and \"indent\" cannot be used together.\"","theme","null","\"pretty-format: Option \"theme\" must not be null.\"","\"object\"","pretty-format: Option \"theme\" must be of type \"object\" but instead received \"","\"."]},"operators":{"distinct":12,"total":33,"identifiers":["()",".","function=>","if","&&","!==","throw","new","===","typeof (prefix)","``","${}"]}},"paramCount":1,"sloc":{"logical":10,"physical":25},"errors":[],"lineEnd":444,"lineStart":420,"name":"validateOptions","paramNames":["options"],"maxNestedMethodDepth":0,"nestedMethods":[]},{"cyclomatic":2,"cyclomaticDensity":66.667,"halstead":{"bugs":0.027,"difficulty":4.444,"effort":363.33,"length":20,"time":20.185,"vocabulary":17,"volume":81.749,"operands":{"distinct":9,"total":10,"identifiers":["Object","prototype","hasOwnProperty","call","DEFAULT_OPTIONS","key","Error","pretty-format: Unknown option \"","\"."]},"operators":{"distinct":8,"total":10,"identifiers":["if","! (prefix)","()",".","throw","new","``","${}"]}},"paramCount":1,"sloc":{"logical":3,"physical":5},"errors":[],"lineEnd":425,"lineStart":421,"name":"<anon method-5>","paramNames":["key"],"maxNestedMethodDepth":0,"nestedMethods":[]},{"cyclomatic":1,"cyclomaticDensity":25,"halstead":{"bugs":0.015,"difficulty":1.5,"effort":67.459,"length":13,"time":3.748,"vocabulary":11,"volume":44.973,"operands":{"distinct":8,"total":8,"identifiers":["Colors","DEFAULT_THEME_KEYS","reduce","colors","key","Object","create","null"]},"operators":{"distinct":3,"total":5,"identifiers":["()",".","function=>"]}},"paramCount":1,"sloc":{"logical":4,"physical":20},"errors":[],"lineEnd":465,"lineStart":446,"name":"<anon method-6>","paramNames":["options"],"maxNestedMethodDepth":0,"nestedMethods":[]},{"cyclomatic":7,"cyclomaticDensity":100,"halstead":{"bugs":0.11,"difficulty":16.5,"effort":5445,"length":66,"time":302.5,"vocabulary":32,"volume":330,"operands":{"distinct":16,"total":33,"identifiers":["value","options","theme","key","undefined","DEFAULT_THEME","color","style","close","\"string\"","open","colors","Error","pretty-format: Option \"theme\" has a key \"","\" whose value \"","\" is undefined in ansi-styles."]},"operators":{"distinct":16,"total":33,"identifiers":["const","=",":?","&&",".","!==","[]","if","else","===","typeof (prefix)","throw","new","``","${}","return"]}},"paramCount":2,"sloc":{"logical":7,"physical":19},"errors":[],"lineEnd":465,"lineStart":447,"name":"<anon method-7>","paramNames":["colors","key"],"maxNestedMethodDepth":0,"nestedMethods":[]},{"cyclomatic":1,"cyclomaticDensity":25,"halstead":{"bugs":0.015,"difficulty":1.5,"effort":67.459,"length":13,"time":3.748,"vocabulary":11,"volume":44.973,"operands":{"distinct":8,"total":8,"identifiers":["Colors","DEFAULT_THEME_KEYS","reduce","colors","key","Object","create","null"]},"operators":{"distinct":3,"total":5,"identifiers":["()",".","function=>"]}},"paramCount":0,"sloc":{"logical":4,"physical":5},"errors":[],"lineEnd":471,"lineStart":467,"name":"<anon method-8>","paramNames":[],"maxNestedMethodDepth":0,"nestedMethods":[]},{"cyclomatic":1,"cyclomaticDensity":25,"halstead":{"bugs":0.014,"difficulty":3.5,"effort":151.148,"length":13,"time":8.397,"vocabulary":10,"volume":43.185,"operands":{"distinct":5,"total":7,"identifiers":["colors","key","close","\"\"","open"]},"operators":{"distinct":5,"total":6,"identifiers":["=","[]","{}",":","return"]}},"paramCount":2,"sloc":{"logical":4,"physical":4},"errors":[],"lineEnd":471,"lineStart":468,"name":"<anon method-9>","paramNames":["colors","key"],"maxNestedMethodDepth":0,"nestedMethods":[]},{"cyclomatic":1,"cyclomaticDensity":100,"halstead":{"bugs":0.005,"difficulty":1.333,"effort":18.575,"length":6,"time":1.032,"vocabulary":5,"volume":13.932,"operands":{"distinct":3,"total":4,"identifiers":["options","printFunctionName","DEFAULT_OPTIONS"]},"operators":{"distinct":2,"total":2,"identifiers":["??","."]}},"paramCount":1,"sloc":{"logical":1,"physical":2},"errors":[],"lineEnd":474,"lineStart":473,"name":"<anon method-10>","paramNames":["options"],"maxNestedMethodDepth":0,"nestedMethods":[]},{"cyclomatic":1,"cyclomaticDensity":100,"halstead":{"bugs":0.005,"difficulty":1.333,"effort":18.575,"length":6,"time":1.032,"vocabulary":5,"volume":13.932,"operands":{"distinct":3,"total":4,"identifiers":["options","escapeRegex","DEFAULT_OPTIONS"]},"operators":{"distinct":2,"total":2,"identifiers":["??","."]}},"paramCount":1,"sloc":{"logical":1,"physical":2},"errors":[],"lineEnd":477,"lineStart":476,"name":"<anon method-11>","paramNames":["options"],"maxNestedMethodDepth":0,"nestedMethods":[]},{"cyclomatic":1,"cyclomaticDensity":100,"halstead":{"bugs":0.005,"difficulty":1.333,"effort":18.575,"length":6,"time":1.032,"vocabulary":5,"volume":13.932,"operands":{"distinct":3,"total":4,"identifiers":["options","escapeString","DEFAULT_OPTIONS"]},"operators":{"distinct":2,"total":2,"identifiers":["??","."]}},"paramCount":1,"sloc":{"logical":1,"physical":2},"errors":[],"lineEnd":480,"lineStart":479,"name":"<anon method-12>","paramNames":["options"],"maxNestedMethodDepth":0,"nestedMethods":[]},{"cyclomatic":6,"cyclomaticDensity":28.571,"halstead":{"bugs":0.2,"difficulty":9.931,"effort":5949.555,"length":115,"time":330.531,"vocabulary":37,"volume":599.087,"operands":{"distinct":29,"total":72,"identifiers":["Config","callToJSON","options","DEFAULT_OPTIONS","colors","highlight","getColorsHighlight","getColorsEmpty","compareKeys","\"function\"","escapeRegex","getEscapeRegex","escapeString","getEscapeString","indent","min","\"\"","createIndent","maxDepth","maxWidth","plugins","printBasicPrototype","true","printFunctionName","getPrintFunctionName","spacingInner","\" \"","\"\n\"","spacingOuter"]},"operators":{"distinct":8,"total":43,"identifiers":["{}",":","??",".",":?","()","===","typeof (prefix)"]}},"paramCount":1,"sloc":{"logical":21,"physical":21},"errors":[],"lineEnd":502,"lineStart":482,"name":"<anon method-13>","paramNames":["options"],"maxNestedMethodDepth":0,"nestedMethods":[]},{"cyclomatic":1,"cyclomaticDensity":50,"halstead":{"bugs":0.011,"difficulty":2.5,"effort":83.048,"length":10,"time":4.614,"vocabulary":10,"volume":33.219,"operands":{"distinct":5,"total":5,"identifiers":["Array","indent","1","join","\" \""]},"operators":{"distinct":5,"total":5,"identifiers":["return","()",".","new","+"]}},"paramCount":1,"sloc":{"logical":2,"physical":3},"errors":[],"lineEnd":506,"lineStart":504,"name":"createIndent","paramNames":["indent"],"maxNestedMethodDepth":0,"nestedMethods":[]},{"cyclomatic":5,"cyclomaticDensity":26.316,"halstead":{"bugs":0.099,"difficulty":8.706,"effort":2587.447,"length":64,"time":143.747,"vocabulary":25,"volume":297.207,"operands":{"distinct":17,"total":37,"identifiers":["options","validateOptions","plugins","plugin","findPlugin","val","null","printPlugin","getConfig","\"\"","0","basicResult","printBasicValue","getPrintFunctionName","getEscapeRegex","getEscapeString","printComplexValue"]},"operators":{"distinct":8,"total":27,"identifiers":["if","()",".","const","=","!==","return","[]"]}},"paramCount":2,"sloc":{"logical":19,"physical":23},"errors":[],"lineEnd":535,"lineStart":513,"name":"format","paramNames":["val","options"],"maxNestedMethodDepth":0,"nestedMethods":[]}]