[{"cyclomatic":2,"cyclomaticDensity":100,"halstead":{"bugs":0.008,"difficulty":1.875,"effort":47.374,"length":9,"time":2.632,"vocabulary":7,"volume":25.266,"operands":{"distinct":4,"total":5,"identifiers":["stream","isTTY","write","\"\u001b[999D\u001b[K\""]},"operators":{"distinct":3,"total":4,"identifiers":["if",".","()"]}},"paramCount":1,"sloc":{"logical":2,"physical":5},"errors":[],"lineEnd":12,"lineStart":8,"name":"clearLine","paramNames":["stream"],"maxNestedMethodDepth":0,"nestedMethods":[]}]